moonmake/__init__.py
moonmake/build_system.py
moonmake/create.py
moonmake/utils.py
moonmake-0.1.532.dist-info/licenses/LICENSE
moonmake-0.1.532.dist-info/METADATA
moonmake-0.1.532.dist-info/WHEEL
moonmake-0.1.532.dist-info/entry_points.txt
moonmake-0.1.532.dist-info/top_level.txt
moonmake-0.1.532.dist-info/RECORD
