Metadata-Version: 2.4
Name: moonmake
Version: 0.1.532
Summary: Sistema de creación de proyectos con comandos rápidos.
Home-page: https://github.com/ranon-rat/moonmake
Author: ranon-rat
Classifier: Programming Language :: Python :: 3
Classifier: License :: OSI Approved :: MIT License
Classifier: Operating System :: OS Independent
Requires-Python: >=3.7
License-File: LICENSE
Requires-Dist: requests==2.32.3
Dynamic: author
Dynamic: classifier
Dynamic: description
Dynamic: description-content-type
Dynamic: home-page
Dynamic: license-file
Dynamic: requires-dist
Dynamic: requires-python
Dynamic: summary
